yaml2py/__init__.py
yaml2py/cli.py
yaml2py/env_loader.py
yaml2py/templates/manager.py.tpl
yaml2py/templates/schema.py.tpl
yaml2py-0.2.0.dist-info/licenses/LICENSE
yaml2py-0.2.0.dist-info/METADATA
yaml2py-0.2.0.dist-info/WHEEL
yaml2py-0.2.0.dist-info/entry_points.txt
yaml2py-0.2.0.dist-info/top_level.txt
yaml2py-0.2.0.dist-info/RECORD
