Metadata-Version: 2.4
Name: yaml2py
Version: 0.2.0
Summary: A CLI tool to generate type-hinted Python config classes from YAML files with nested structure support.
Author-email: JonesHong <latte831104@example.com>
License: MIT License
Project-URL: Homepage, https://github.com/joneshong/yaml2py
Project-URL: Bug Tracker, https://github.com/joneshong/yaml2py/issues
Classifier: Programming Language :: Python :: 3
Classifier: License :: OSI Approved :: MIT License
Classifier: Operating System :: OS Independent
Classifier: Development Status :: 3 - Alpha
Classifier: Environment :: Console
Classifier: Intended Audience :: Developers
Classifier: Topic :: Software Development :: Code Generators
Classifier: Topic :: Utilities
Requires-Python: >=3.8
License-File: LICENSE
Requires-Dist: click>=8.0
Requires-Dist: watchdog>=2.1.6
Requires-Dist: pyyaml>=6.0
Dynamic: license-file
